[
  {
    "title": "Das Erste",
    "thumbnail": "https://lo1.in/ger/dsr1.png",
    "link(HD)": "http://italians-app.net:8080/cognato-kissin/kdDsFglR544/56953"
  },
  {
    "title": "ZDF",
    "thumbnail": "https://lo1.in/oly/ded.png",
    "link(HD)": "http://italians-app.net:8080/cognato-kissin/kdDsFglR544/56954"
  },
  {
    "title": "RTL",
    "thumbnail": "https://lo1.in/ger/rtl0.png",
    "link(HD)": "http://italians-app.net:8080/cognato-kissin/kdDsFglR544/56958"
  },
  {
    "title": "RTLZWEI",
    "thumbnail": "https://lo1.in/ger/rtl0.png",
    "link(HEVC)": "http://italians-app.net:8080/cognato-kissin/kdDsFglR544/56959"
  },
  {
    "title": "Sat.1",
    "thumbnail": "https://lo1.in/ger/satt1.png",
    "link(HD)": "http://italians-app.net:8080/cognato-kissin/kdDsFglR544/56955"
  },
  {
    "title": "Prosieben",
    "thumbnail": "https://lo1.in/ger/prsbn.png",
    "link(HD)": "http://italians-app.net:8080/cognato-kissin/kdDsFglR544/56965"
  },
  {
    "title": "VOX",
    "thumbnail": "https://lo1.in/ger/voxx.png",
    "link(HD)": "http://italians-app.net:8080/cognato-kissin/kdDsFglR544/56972"
  },
  {
    "title": "VOXup",
    "thumbnail": "https://lo1.in/ger/voxx.png",
    "link(HD)": "http://italians-app.net:8080/cognato-kissin/kdDsFglR544/81673"
  },
  {
    "title": "kabel eins",
    "thumbnail": "https://lo1.in/ger/kabl.png",
    "link(HD)": "http://italians-app.net:8080/cognato-kissin/kdDsFglR544/56969"
  },
  {
    "title": "ProSieben Maxx",
    "thumbnail": "https://lo1.in/ger/prbnmm.png",
    "link(HD)": "http://italians-app.net:8080/cognato-kissin/kdDsFglR544/56965"
  },
  {
    "title": "ProSieben FUN",
    "thumbnail": "https://lo1.in/ger/prs.png",
    "link(HD)": "http://italians-app.net:8080/cognato-kissin/kdDsFglR544/56967"
  },
  {
    "title": "RTL Living",
    "thumbnail": "https://lo1.in/ger/rtlvi.png",
    "link(HD)": "http://italians-app.net:8080/cognato-kissin/kdDsFglR544/56962"
  },
  {
    "title": "RTL Crime",
    "thumbnail": "https://lo1.in/ger/rtlcrm.png",
    "link(HD)": "http://italians-app.net:8080/cognato-kissin/kdDsFglR544/56961"
  },
  {
    "title": "RTL Passion",
    "thumbnail": "https://lo1.in/ger/rtlpa.png",
    "link(HD)": "http://italians-app.net:8080/cognato-kissin/kdDsFglR544/56964"
  },
  {
    "title": "RTLup",
    "thumbnail": "https://lo1.in/ger/RTL UP.png",
    "link(HD)": "http://italians-app.net:8080/cognato-kissin/kdDsFglR544/81674"
  },
  {
    "title": "Sixx",
    "thumbnail": "https://lo1.in/ger/six.png",
    "link(HD)": "http://italians-app.net:8080/cognato-kissin/kdDsFglR544/56973"
  },
  {
    "title": "Sat.1 Emotions",
    "thumbnail": "https://lo1.in/ger/niedbaa.png",
    "link(HD)": "http://italians-app.net:8080/cognato-kissin/kdDsFglR544/56955"
  },
  {
    "title": "ARTE",
    "thumbnail": "https://lo1.in/ger/art.png",
    "link(HD)": "http://italians-app.net:8080/cognato-kissin/kdDsFglR544/56984"
  },
  {
    "title": "Servus TV Österreich",
    "thumbnail": "https://lo1.in/ger/srvv.png",
    "link(HD)": "http://italians-app.net:8080/cognato-kissin/kdDsFglR544/57018"
  },
  {
    "title": "Tele 5",
    "thumbnail": "https://lo1.in/ger/tel5.png",
    "link(HD)": "http://italians-app.net:8080/cognato-kissin/kdDsFglR544/56979"
  },
  {
    "title": "3sat",
    "thumbnail": "https://lo1.in/ger/sat.png",
    "link(HD)": "http://italians-app.net:8080/cognato-kissin/kdDsFglR544/56974"
  },
  {
    "title": "Sky Nature",
    "thumbnail": "https://lo1.in/ger/SKY NATURE.png",
    "link(HD)": "http://italians-app.net:8080/cognato-kissin/kdDsFglR544/57049"
  },
  {
    "title": "Sky Documentaries",
    "thumbnail": "https://lo1.in/ger/skysern.png",
    "link(HD)": "http://italians-app.net:8080/cognato-kissin/kdDsFglR544/57050"
  },
  {
    "title": "WELT",
    "thumbnail": "https://lo1.in/ger/welth.png",
    "link(HD)": "http://italians-app.net:8080/cognato-kissin/kdDsFglR544/57091"
  },
  {
    "title": "ntv",
    "thumbnail": "https://lo1.in/ger/ntv.png",
    "link(HD)": "http://italians-app.net:8080/cognato-kissin/kdDsFglR544/56996"
  },
  {
    "title": "DMAX",
    "thumbnail": "https://lo1.in/sp/dmaxx.png",
    "link(HD)": "http://italians-app.net:8080/cognato-kissin/kdDsFglR544/57043"
  },
  {
    "title": "Sky Crime",
    "thumbnail": "https://lo1.in/ger/SKY CI.png",
    "link(HD)": "http://italians-app.net:8080/cognato-kissin/kdDsFglR544/57074"
  },
  {
    "title": "Sky Cinema Premiere HD",
    "thumbnail": "https://lo1.in/ger/skycnprm.png",
    "link(HD)": "http://italians-app.net:8080/cognato-kissin/kdDsFglR544/57062"
  },
  {
    "title": "Sky Cinema Action HD",
    "thumbnail": "https://lo1.in/ger/skycnact.png",
    "link(HD)": "http://italians-app.net:8080/cognato-kissin/kdDsFglR544/57060"
  },
  {
    "title": "Sky Cinema Family HD",
    "thumbnail": "https://lo1.in/ger/skycnfm.png",
    "link(HD)": "http://italians-app.net:8080/cognato-kissin/kdDsFglR544/57067"
  },
  {
    "title": "Sky Cinema Classics HD",
    "thumbnail": "https://lo1.in/ger/skycbcla.png",
    "link(HD)": "http://italians-app.net:8080/cognato-kissin/kdDsFglR544/57066"
  },
  {
    "title": "Sky Cinema Best Of",
    "thumbnail": "https://lo1.in/ger/skycn.png",
    "link(HD)": "http://italians-app.net:8080/cognato-kissin/kdDsFglR544/57060"
  },
  {
    "title": "Sky Atlantic HD",
    "thumbnail": "https://lo1.in/ger/skylan.png",
    "link(HD)": "http://italians-app.net:8080/cognato-kissin/kdDsFglR544/57072"
  },
  {
    "title": "Sky Krimi",
    "thumbnail": "https://lo1.in/ger/skykr.png",
    "link(HD)": "http://italians-app.net:8080/cognato-kissin/kdDsFglR544/57075"
  },
  {
    "title": "Sky Replay",
    "thumbnail": "https://lo1.in/ger/foxs.png",
    "link(HD)": "http://italians-app.net:8080/cognato-kissin/kdDsFglR544/57073"
  },
  {
    "title": "Warner TV Comedy",
    "thumbnail": "https://lo1.in/ger/wartv11.png",
    "link(HD)": "http://italians-app.net:8080/cognato-kissin/kdDsFglR544/57095"
  },
  {
    "title": "Warner TV Film",
    "thumbnail": "https://lo1.in/ger/wartv12.png",
    "link(HD)": "http://italians-app.net:8080/cognato-kissin/kdDsFglR544/57092"
  },
  {
    "title": "Warner TV Serie",
    "thumbnail": "https://lo1.in/ger/wartv00.png",
    "link(HD)": "http://italians-app.net:8080/cognato-kissin/kdDsFglR544/57093"
  },
  {
    "title": "COMEDY CENTRAL",
    "thumbnail": "https://lo1.in/ger/cmdcntt.png",
    "link(HD)": "http://italians-app.net:8080/cognato-kissin/kdDsFglR544/57068"
  },
  {
    "title": "Sky Sport Bundesliga 1",
    "thumbnail": "https://lo1.in/ger/skyspd1.png",
    "link(HD)": "http://italians-app.net:8080/cognato-kissin/kdDsFglR544/56990"
  },
  {
    "title": "Sky Sport Bundesliga 2",
    "thumbnail": "https://lo1.in/ger/skyspd1.png",
    "link(HD)": "http://italians-app.net:8080/cognato-kissin/kdDsFglR544/57146"
  },
  {
    "title": "Sky Sport Bundesliga 3",
    "thumbnail": "https://lo1.in/ger/skyspd1.png",
    "link(HD)": "http://italians-app.net:8080/cognato-kissin/kdDsFglR544/57147"
  },
  {
    "title": "Sky Sport Bundesliga 4",
    "thumbnail": "https://lo1.in/ger/skyspd1.png",
    "link(HD)": "http://italians-app.net:8080/cognato-kissin/kdDsFglR544/57148"
  },
  {
    "title": "Sky Sport Bundesliga 5",
    "thumbnail": "https://lo1.in/ger/skyspd1.png",
    "link(HD)": "http://italians-app.net:8080/cognato-kissin/kdDsFglR544/57149"
  },
  {
    "title": "Sky Sport Bundesliga 6",
    "thumbnail": "https://lo1.in/ger/skyspd1.png",
    "link(HD)": "http://italians-app.net:8080/cognato-kissin/kdDsFglR544/57150"
  },
  {
    "title": "Sky Sport Bundesliga 7",
    "thumbnail": "https://lo1.in/ger/skyspd1.png",
    "link(HD)": "http://italians-app.net:8080/cognato-kissin/kdDsFglR544/57151"
  },
  {
    "title": "Sky Sport Bundesliga 8",
    "thumbnail": "https://lo1.in/ger/skyspd1.png",
    "link(HD)": "http://italians-app.net:8080/cognato-kissin/kdDsFglR544/57152"
  },
  {
    "title": "Sky Sport Bundesliga 9",
    "thumbnail": "https://lo1.in/ger/skyspd1.png",
    "link(HD)": "http://italians-app.net:8080/cognato-kissin/kdDsFglR544/57153"
  },
  {
    "title": "Sky Sport Bundesliga 10",
    "thumbnail": "https://lo1.in/ger/skyspd1.png",
    "link(HD)": "http://italians-app.net:8080/cognato-kissin/kdDsFglR544/57154"
  },
  {
    "title": "Dazn",
    "thumbnail": "https://lo1.in/ger/DAZN NBA.png",
    "link(HD)": "http://italians-app.net:8080/cognato-kissin/kdDsFglR544/57121"
  },
  {
    "title": "DAZN 1",
    "thumbnail": "https://lo1.in/ger/daznbbb.png",
    "link(HD)": "http://italians-app.net:8080/cognato-kissin/kdDsFglR544/57121"
  },
  {
    "title": "DAZN 2",
    "thumbnail": "https://lo1.in/ger/dz2br.png",
    "link(HD)": "http://italians-app.net:8080/cognato-kissin/kdDsFglR544/57123"
  },
  {
    "title": "Sky Sport 1",
    "thumbnail": "https://lo1.in/ger/skysp.png",
    "link(HD)": "http://italians-app.net:8080/cognato-kissin/kdDsFglR544/57140"
  },
  {
    "title": "Sky Sport 2",
    "thumbnail": "https://lo1.in/ger/skysp2.png",
    "link(HD)": "http://italians-app.net:8080/cognato-kissin/kdDsFglR544/57141"
  },
  {
    "title": "Sky Sport 3",
    "thumbnail": "https://lo1.in/ger/skysp2.png",
    "link(HD)": "http://italians-app.net:8080/cognato-kissin/kdDsFglR544/57133"
  },
  {
    "title": "Sky Sport 4",
    "thumbnail": "https://lo1.in/ger/skysp2.png",
    "link(HD)": "http://italians-app.net:8080/cognato-kissin/kdDsFglR544/57134"
  },
  {
    "title": "Sky Sport 5",
    "thumbnail": "https://lo1.in/ger/skysp2.png",
    "link(HD)": "http://italians-app.net:8080/cognato-kissin/kdDsFglR544/57135"
  },
  {
    "title": "Sky Sport 6",
    "thumbnail": "https://lo1.in/ger/skysp2.png",
    "link(HD)": "http://italians-app.net:8080/cognato-kissin/kdDsFglR544/57136"
  },
  {
    "title": "Sky Sport 7",
    "thumbnail": "https://lo1.in/ger/skysp2.png",
    "link(HD)": "http://italians-app.net:8080/cognato-kissin/kdDsFglR544/57137"
  },
  {
    "title": "Sky Sport 8",
    "thumbnail": "https://lo1.in/ger/skysp2.png",
    "link(HD)": "http://italians-app.net:8080/cognato-kissin/kdDsFglR544/57138"
  },
  {
    "title": "Sky Sport 9",
    "thumbnail": "https://lo1.in/ger/skysp2.png",
    "link(HD)": "http://italians-app.net:8080/cognato-kissin/kdDsFglR544/57139"
  },
  {
    "title": "Sky Sports News",
    "thumbnail": "https://lo1.in/ger/skyspns.png",
    "link(HD)": "http://italians-app.net:8080/cognato-kissin/kdDsFglR544/57112"
  },
  {
    "title": "Sky Sport F1",
    "thumbnail": "https://lo1.in/ger/skyspf.png",
    "link(HD)": "http://italians-app.net:8080/cognato-kissin/kdDsFglR544/57126"
  },
  {
    "title": "Sky Sport Tennis",
    "thumbnail": "https://lo1.in/ger/SKY SPORT TENNIS.png",
    "link(HD)": "http://italians-app.net:8080/cognato-kissin/kdDsFglR544/57131"
  },
  {
    "title": "Sky Sport Premier League",
    "thumbnail": "https://lo1.in/ger/SKY SPORT PREMIER LEAGUE.png",
    "link(HD)": "http://italians-app.net:8080/cognato-kissin/kdDsFglR544/57125"
  },
  {
    "title": "Sky Sport Mix",
    "thumbnail": "https://lo1.in/ger/SKY SPORT MIX.png",
    "link(HD)": "http://italians-app.net:8080/cognato-kissin/kdDsFglR544/57128"
  },
  {
    "title": "Sky Sport Golf",
    "thumbnail": "https://lo1.in/ger/SKY SPORT GOLF.png",
    "link(HD)": "http://italians-app.net:8080/cognato-kissin/kdDsFglR544/57127"
  },
  {
    "title": "EuroSport 1",
    "thumbnail": "https://lo1.in/ger/daznbbb.png",
    "link(HD)": "http://italians-app.net:8080/cognato-kissin/kdDsFglR544/57118"
  },
  {
    "title": "Eurosport 2",
    "thumbnail": "https://lo1.in/ger/EUROSPORTt.png",
    "link(HD)": "http://italians-app.net:8080/cognato-kissin/kdDsFglR544/57119"
  },
  {
    "title": "SPORT1",
    "thumbnail": "https://lo1.in/ger/spp1.png",
    "link(HD)": "http://italians-app.net:8080/cognato-kissin/kdDsFglR544/57113"
  },
  {
    "title": "DYN SPORT 1",
    "thumbnail": "https://lo1.in/ger/DYN.png",
    "link(HD)": "http://italians-app.net:8080/cognato-kissin/kdDsFglR544/57113"
  },
  {
    "title": "DYN SPORT 2",
    "thumbnail": "https://lo1.in/ger/DYN.png",
    "link(HD)": "http://italians-app.net:8080/cognato-kissin/kdDsFglR544/57141"
  },
  {
    "title": "DYN SPORT 3",
    "thumbnail": "https://lo1.in/ger/DYN.png",
    "link(HD)": "http://italians-app.net:8080/cognato-kissin/kdDsFglR544/57133"
  },
  {
    "title": "DYN SPORT 4",
    "thumbnail": "https://lo1.in/ger/DYN.png",
    "link(HD)": "http://italians-app.net:8080/cognato-kissin/kdDsFglR544/57134"
  },
  {
    "title": "DYN SPORT 5",
    "thumbnail": "https://lo1.in/ger/DYN.png",
    "link(HD)": "http://italians-app.net:8080/cognato-kissin/kdDsFglR544/57135"
  },
  {
    "title": "DYN SPORT 6",
    "thumbnail": "https://lo1.in/ger/DYN.png",
    "link(HD)": "http://italians-app.net:8080/cognato-kissin/kdDsFglR544/57136"
  },
  {
    "title": "DYN SPORT 7",
    "thumbnail": "https://lo1.in/ger/DYN.png",
    "link(HD)": "http://italians-app.net:8080/cognato-kissin/kdDsFglR544/57137"
  },
  {
    "title": "DYN SPORT 8",
    "thumbnail": "https://lo1.in/ger/DYN.png",
    "link(HD)": "http://italians-app.net:8080/cognato-kissin/kdDsFglR544/57138"
  },
  {
    "title": "DYN SPORT 9",
    "thumbnail": "https://lo1.in/ger/DYN.png",
    "link(HD)": "http://italians-app.net:8080/cognato-kissin/kdDsFglR544/57139"
  },
  {
    "title": "DYN SPORT 10",
    "thumbnail": "https://lo1.in/ger/DYN.png",
    "link(HD)": "http://italians-app.net:8080/cognato-kissin/kdDsFglR544/57113"
  },
  {
    "title": "DYN SPORT 11",
    "thumbnail": "https://lo1.in/ger/DYN.png",
    "link(HD)": "http://italians-app.net:8080/cognato-kissin/kdDsFglR544/57113"
  },
  {
    "title": "DYN SPORT 12",
    "thumbnail": "https://lo1.in/ger/DYN.png",
    "link(HD)": "http://italians-app.net:8080/cognato-kissin/kdDsFglR544/57113"
  },
  {
    "title": "DYN SPORT 13",
    "thumbnail": "https://lo1.in/ger/DYN.png",
    "link(HD)": "http://italians-app.net:8080/cognato-kissin/kdDsFglR544/57113"
  },
  {
    "title": "DYN SPORT 14",
    "thumbnail": "https://lo1.in/ger/DYN.png",
    "link(HD)": "http://italians-app.net:8080/cognato-kissin/kdDsFglR544/57113"
  },
  {
    "title": "DYN SPORT 15",
    "thumbnail": "https://lo1.in/ger/DYN.png",
    "link(HD)": "http://italians-app.net:8080/cognato-kissin/kdDsFglR544/57113"
  },
  {
    "title": "sky Sport Austria 1 HD",
    "thumbnail": "https://lo1.in/ger/skyspau.png",
    "link(HD)": "http://italians-app.net:8080/cognato-kissin/kdDsFglR544/57021"
  },
  {
    "title": "sky Sport Austria 2 HD",
    "thumbnail": "https://lo1.in/ger/skyspau.png",
    "link(HD)": "http://italians-app.net:8080/cognato-kissin/kdDsFglR544/57023"
  },
  {
    "title": "sky Sport Austria 3 HD",
    "thumbnail": "https://lo1.in/ger/skyspau.png",
    "link(HD)": "http://italians-app.net:8080/cognato-kissin/kdDsFglR544/57025"
  },
  {
    "title": "sky Sport Austria 4 HD",
    "thumbnail": "https://lo1.in/ger/skyspau.png",
    "link(HD)": "http://italians-app.net:8080/cognato-kissin/kdDsFglR544/57026"
  },
  {
    "title": "sky Sport Austria 5 HD",
    "thumbnail": "https://lo1.in/ger/skyspau.png",
    "link(HD)": "http://italians-app.net:8080/cognato-kissin/kdDsFglR544/81633"
  },
  {
    "title": "sky Sport Austria 6 HD",
    "thumbnail": "https://lo1.in/ger/skyspau.png",
    "link(HD)": "http://italians-app.net:8080/cognato-kissin/kdDsFglR544/81634"
  },
  {
    "title": "sky Sport Austria 7 HD",
    "thumbnail": "https://lo1.in/ger/skyspau.png",
    "link(HD)": "http://italians-app.net:8080/cognato-kissin/kdDsFglR544/81635"
  },
  {
    "title": "sky Sport Austria 8 HD",
    "thumbnail": "https://lo1.in/ger/skyspau.png",
    "link(HD)": "http://italians-app.net:8080/cognato-kissin/kdDsFglR544/57021"
  }
]
